oculus/__init__.py
oculus-0.0.2.dist-info/METADATA
oculus-0.0.2.dist-info/WHEEL
oculus-0.0.2.dist-info/top_level.txt
oculus-0.0.2.dist-info/RECORD
