Metadata-Version: 2.1
Name: oculus
Version: 0.0.2
Summary: Python library for lighting
Author-email: constexpr <constexpr@lumin.sh>
Classifier: Programming Language :: Python :: 3
Classifier: License :: OSI Approved :: MIT License
Classifier: Operating System :: OS Independent
Requires-Python: >=3.8
Requires-Dist: numpy
